test_test/__init__.py
test_test/test_tisc.py
tisc/__init__.py
tisc/tisc.py
tisc/modules/BiLSTM.py
tisc/modules/LSTM.py
tisc/modules/Transformer.py
tisc/modules/__init__.py
tisc/modules/head/__init__.py
tisc/modules/head/head.py
tisc/modules/utils/__init__.py
tisc/modules/utils/builder.py
tisc-0.1.2.dist-info/licenses/LICENSE
tisc-0.1.2.dist-info/METADATA
tisc-0.1.2.dist-info/WHEEL
tisc-0.1.2.dist-info/top_level.txt
tisc-0.1.2.dist-info/RECORD
