Metadata-Version: 2.4
Name: tisc
Version: 0.1.2
Summary: Simple model creation and training framework for time series classification in Pytorch
Home-page: https://github.com/Yutsuro/pytorch-time-series-classification
Author: Yutsuro
Author-email: Yuki@utsu.ro
License: Apache
Keywords: Pytorch Time-Series-Classification LSTM BiLSTM Transformer Machine-Learning Deep-Learning AI Artificial-Intelligence
Classifier: Programming Language :: Python :: 3
Classifier: Programming Language :: Python :: 3.6
Classifier: Programming Language :: Python :: 3.7
Classifier: Programming Language :: Python :: 3.8
Classifier: Programming Language :: Python :: 3.9
Classifier: Programming Language :: Python :: 3.10
Classifier: Programming Language :: Python :: 3.11
Classifier: Programming Language :: Python :: 3.12
Classifier: Programming Language :: Python :: 3 :: Only
Classifier: Topic :: Software Development :: Libraries :: Python Modules
License-File: LICENSE
Requires-Dist: matplotlib>=3.8.3
Requires-Dist: numpy<2.0,>=1.19.5
Requires-Dist: scikit_learn>=1.4.1
Requires-Dist: seaborn>=0.13.2
Requires-Dist: matplotlib-fontja>=1.1.0
Dynamic: author
Dynamic: author-email
Dynamic: classifier
Dynamic: description
Dynamic: description-content-type
Dynamic: home-page
Dynamic: keywords
Dynamic: license
Dynamic: license-file
Dynamic: requires-dist
Dynamic: summary
